mdx_mathjax.py
python_markdown_mathjax-1.0.4.dist-info/DESCRIPTION.rst
python_markdown_mathjax-1.0.4.dist-info/METADATA
python_markdown_mathjax-1.0.4.dist-info/RECORD
python_markdown_mathjax-1.0.4.dist-info/WHEEL
python_markdown_mathjax-1.0.4.dist-info/metadata.json
python_markdown_mathjax-1.0.4.dist-info/top_level.txt
