Metadata-Version: 2.0
Name: python-markdown-mathjax
Version: 1.0.4
Summary: MathJax extension for python-markdown
Home-page: https://github.com/liuyug/python-markdown-mathjax.git
Author: Yugang LIU
Author-email: liuyug@gmail.com
License: MIT
Platform: UNKNOWN
Requires-Dist: Markdown (>=2.5)
